rtl/i2s_rx.sv
/* I2S RECEIVER MODULE:- 
    sys_clk is the main clock of the chip running at 50mhz or 100mhz
    rst_n active low reset, when it drops to 0, all counters and shift registers turn empty
    sclk is the slower clock which watches over our input data
    lrclk indicates which channel the data goes, our module detects shift in this and creates a new starting point for the DF
    sd is the actual data bits 

*/
module i2s_rx #(
    parameter DATA_WIDTH = 24,
    parameter FRAME_WIDTH = 32
    )(
    input wire sys_clk,
    input wire sclk,

    input wire lrclk,
    input wire sd,
    input wire rst_n,

    output reg [DATA_WIDTH-1:0] left_data,
    output reg [DATA_WIDTH-1:0] right_data,
    output reg valid
);

//we have sclk coming from external world, hence we oversample it using in-house 50mhz clock to synchronize and avoid metastability

reg sff1, sff2, sff3;
always @(posedge sys_clk or negedge rst_n) begin
    if (!rst_n) begin
        sff1 <= 1'b0;
        sff2 <= 1'b0;
        sff3 <= 1'b0;
    end
    else begin
        sff1 <= sclk;   // raw wire input
        sff2 <= sff1;   // current state
        sff3 <= sff2;   // past state
    end
end
wire sclk_rise = (sff2 == 1'b1) && (sff3 == 1'b0); // checks if current state is 1, and previous state is 0


//we have lrclk coming from the external world aswell, hence oversampling must be done here aswell

reg lrff1, lrff2, lrff3;
always @(posedge sys_clk or negedge rst_n) begin
    if(!rst_n) begin
        lrff1 <= 1'b0;
        lrff2 <= 1'b0;
        lrff3 <= 1'b0;
    end
    else begin
        lrff1 <= lrclk;
        lrff2 <= lrff1;
        lrff3 <= lrff2;
    end
end
wire lrclk_toggle = (lrff2 != lrff3); // we get to know when lrclk is toggled when we compare the past and present states of them


// sd is also coming from external source hence we must synhronize (but no edge detection required)

reg sdff1, sdff2;
always @(posedge sys_clk or negedge rst_n) begin
    if(!rst_n) begin
        sdff1 <= 1'b0;
        sdff2 <= 1'b0;
    end
    else begin
        sdff1 <= sd;
        sdff2 <= sdff1;
    end
end

// Creating a 32 bit counter to keep in track the data bits going into the sipo

reg [5:0] counter;
always @(posedge sys_clk or negedge rst_n) begin
    if (!rst_n) begin
        counter <= 6'b0;
    end
    else if (lrclk_toggle) begin
        counter <= 6'b0;
    end
    else if (sclk_rise) begin
        counter <= counter + 1'b1;
    end
end
wire shift_enable;
assign shift_enable = sclk_rise && (counter >= 6'b1) && (counter <= DATA_WIDTH);



//shift register accepts the serial data bits and converts and stores it as 24 bit parallel data

reg [DATA_WIDTH-1:0] shift_reg;
always @(posedge sys_clk or negedge rst_n) begin
    if (!rst_n) begin
        shift_reg <= {(DATA_WIDTH){1'b0}};
    end
    else if (shift_enable) begin 
        shift_reg <= {shift_reg[DATA_WIDTH-2:0], sdff2};
    end
end

always @(posedge sys_clk or negedge rst_n) begin
    if(!rst_n) begin
        left_data <= {(DATA_WIDTH){1'b0}};
        right_data <= {(DATA_WIDTH){1'b0}};
        valid <= 1'b0;
    end
    else begin
        valid <= 1'b0;
        if (lrclk_toggle) begin
            if (lrff3 == 1'b0) begin
                left_data <= shift_reg;
            end 
            else begin
                right_data <= shift_reg;
                valid <= 1'b1;
            end
        end
    end
end

endmodule

tb/i2s_rx/i2s_rx_tb.sv
`timescale 1ns / 1ps

module tb_i2s_rx();

    // Parameters
    localparam DATA_WIDTH = 24;
    localparam FRAME_WIDTH = 32;

    // DUT Signals
    reg sys_clk;
    reg sclk;
    reg lrclk;
    reg sd;
    reg rst_n;

    wire [DATA_WIDTH-1:0] left_data;
    wire [DATA_WIDTH-1:0] right_data;
    wire valid;

    // Instantiate the Device Under Test (DUT)
    i2s_rx #(
        .DATA_WIDTH(DATA_WIDTH),
        .FRAME_WIDTH(FRAME_WIDTH)
    ) dut (
        .sys_clk(sys_clk),
        .sclk(sclk),
        .lrclk(lrclk),
        .sd(sd),
        .rst_n(rst_n),
        .left_data(left_data),
        .right_data(right_data),
        .valid(valid)
    );

    // Clock Generation (50 MHz sys_clk)
    initial sys_clk = 0;
    always #10 sys_clk = ~sys_clk;

    // Clock Generation (~3 MHz sclk)
    initial sclk = 0;
    always #160 sclk = ~sclk;

    // Task to send a single I2S frame (Left or Right)
    task send_frame(input logic [DATA_WIDTH-1:0] payload, input logic channel);
        integer i;
        begin
            // 1. Wait for the falling edge before changing ANY signals!
            @(negedge sclk);
            
            // 2. Change lrclk and send the dummy bit at the exact same time
            lrclk = channel;
            sd = 1'b0; 

            // 3. Send the 24-bit payload, MSB first
            for (i = DATA_WIDTH-1; i >= 0; i = i - 1) begin
                @(negedge sclk); // Change data on the falling edge
                sd = payload[i]; // Receiver captures it on the rising edge
            end

            // 4. Send the remaining padding bits (FRAME_WIDTH - DATA_WIDTH - 1)
            for (i = 0; i < (FRAME_WIDTH - DATA_WIDTH - 1); i = i + 1) begin
                @(negedge sclk);
                sd = 1'b0;
            end
            
            // Wait for the final rising edge of the frame to complete
            @(posedge sclk);
        end
    endtask

    // Main Test Sequence
    initial begin
        // Initialize signals
        lrclk = 1'b1; // Start high so toggling to 0 starts the Left channel
        sd = 1'b0;
        rst_n = 1'b0;

        // Apply Reset
        #100;
        @(posedge sys_clk);
        rst_n = 1'b1;

        // Send Left Channel Data: 24'hAABBCC
        send_frame(24'hAABBCC, 1'b0);

        // Send Right Channel Data: 24'h112233
        send_frame(24'h112233, 1'b1);

        // Send a dummy Left frame to let the Right channel finish and fire the 'valid' pulse
        send_frame(24'h000000, 1'b0);

        send_frame(24'h123456, 1'b1);

        #1000000
        // Let the simulation run for a few more clocks to observe outputs
        #500;
        $finish;
    end

    // Waveform dumping for GTKWave or similar viewers
    initial begin
        $dumpfile("sim/i2s_rx/i2s_rx.vcd");
        $dumpvars(0, tb_i2s_rx);
    end

endmodule

sim/i2s_rx/i2s_rx.vcd
$date
	Fri Aug 21 10:45:41 2026
$end
$version
	Icarus Verilog
$end
$timescale
	1ps
$end
$scope module tb_i2s_rx $end
$var wire 1 ! valid $end
$var wire 24 " right_data [23:0] $end
$var wire 24 # left_data [23:0] $end
$var parameter 32 $ DATA_WIDTH $end
$var parameter 32 % FRAME_WIDTH $end
$var reg 1 & lrclk $end
$var reg 1 ' rst_n $end
$var reg 1 ( sclk $end
$var reg 1 ) sd $end
$var reg 1 * sys_clk $end
$scope module dut $end
$var wire 1 & lrclk $end
$var wire 1 + lrclk_toggle $end
$var wire 1 ' rst_n $end
$var wire 1 ( sclk $end
$var wire 1 , sclk_rise $end
$var wire 1 ) sd $end
$var wire 1 - shift_enable $end
$var wire 1 * sys_clk $end
$var parameter 32 . DATA_WIDTH $end
$var parameter 32 / FRAME_WIDTH $end
$var reg 6 0 counter [5:0] $end
$var reg 24 1 left_data [23:0] $end
$var reg 1 2 lrff1 $end
$var reg 1 3 lrff2 $end
$var reg 1 4 lrff3 $end
$var reg 24 5 right_data [23:0] $end
$var reg 1 6 sdff1 $end
$var reg 1 7 sdff2 $end
$var reg 1 8 sff1 $end
$var reg 1 9 sff2 $end
$var reg 1 : sff3 $end
$var reg 24 ; shift_reg [23:0] $end
$var reg 1 ! valid $end
$upscope $end
$scope task send_frame $end
$var reg 1 < channel $end
$var reg 24 = payload [23:0] $end
$var integer 32 > i [31:0] $end
$upscope $end
$upscope $end
$enddefinitions $end
$comment Show the parameter values. $end
$dumpall
b100000 /
b11000 .
b100000 %
b11000 $
$end
#0
$dumpvars
bx >
bx =
x<
b0 ;
0:
09
08
07
06
b0 5
04
03
02
b0 1
b0 0
0-
0,
0+
0*
0)
0(
0'
1&
b0 #
b0 "
0!
$end
#10000
1*
#20000
0*
#30000
1*
#40000
0*
#50000
1*
#60000
0*
#70000
1*
#80000
0*
#90000
1*
#100000
0*
#110000
12
0<
b101010101011101111001100 =
1'
1*
#120000
0*
#130000
1+
13
1*
#140000
0*
#150000
0+
14
1*
#160000
0*
1(
#170000
18
1*
#180000
0*
#190000
1,
19
1*
#200000
0*
#210000
0-
0,
b1 0
1:
1*
#220000
0*
#230000
1*
#240000
0*
#250000
1*
#260000
0*
#270000
1*
#280000
0*
#290000
1*
#300000
0*
#310000
1*
#320000
b10111 >
0&
0*
0(
#330000
02
08
1*
#340000
0*
#350000
1+
09
03
1*
#360000
0*
#370000
0+
1!
b0 0
04
0:
1*
#380000
0*
#390000
0!
1*
#400000
0*
#410000
1*
#420000
0*
#430000
1*
#440000
0*
#450000
1*
#460000
0*
#470000
1*
#480000
0*
1(
#490000
18
1*
#500000
0*
#510000
1,
19
1*
#520000
0*
#530000
0-
0,
b1 0
1:
1*
#540000
0*
#550000
1*
#560000
0*
#570000
1*
#580000
0*
#590000
1*
#600000
0*
#610000
1*
#620000
0*
#630000
1*
#640000
b10110 >
1)
0*
0(
#650000
16
08
1*
#660000
0*
#670000
09
17
1*
#680000
0*
#690000
0:
1*
#700000
0*
#710000
1*
#720000
0*
#730000
1*
#740000
0*
#750000
1*
#760000
0*
#770000
1*
#780000
0*
#790000
1*
#800000
0*
1(
#810000
18
1*
#820000
0*
#830000
1-
1,
19
1*
#840000
0*
#850000
0-
0,
b1 ;
b10 0
1:
1*
#860000
0*
#870000
1*
#880000
0*
#890000
1*
#900000
0*
#910000
1*
#920000
0*
#930000
1*
#940000
0*
#950000
1*
#960000
b10101 >
0)
0*
0(
#970000
06
08
1*
#980000
0*
#990000
09
07
1*
#1000000
0*
#1010000
0:
1*
#1020000
0*
#1030000
1*
#1040000
0*
#1050000
1*
#1060000
0*
#1070000
1*
#1080000
0*
#1090000
1*
#1100000
0*
#1110000
1*
#1120000
0*
1(
#1130000
18
1*
#1140000
0*
#1150000
1-
1,
19
1*
#1160000
0*
#1170000
0-
0,
b10 ;
b11 0
1:
1*
#1180000
0*
#1190000
1*
#1200000
0*
#1210000
1*
#1220000
0*
#1230000
1*
#1240000
0*
#1250000
1*
#1260000
0*
#1270000
1*
#1280000
b10100 >
1)
0*
0(
#1290000
16
08
1*
#1300000
0*
#1310000
09
17
1*
#1320000
0*
#1330000
0:
1*
#1340000
0*
#1350000
1*
#1360000
0*
#1370000
1*
#1380000
0*
#1390000
1*
#1400000
0*
#1410000
1*
#1420000
0*
#1430000
1*
#1440000
0*
1(
#1450000
18
1*
#1460000
0*
#1470000
1-
1,
19
1*
#1480000
0*
#1490000
0-
0,
b101 ;
b100 0
1:
1*
#1500000
0*
#1510000
1*
#1520000
0*
#1530000
1*
#1540000
0*
#1550000
1*
#1560000
0*
#1570000
1*
#1580000
0*
#1590000
1*
#1600000
b10011 >
0)
0*
0(
#1610000
06
08
1*
#1620000
0*
#1630000
09
07
1*
#1640000
0*
#1650000
0:
1*
#1660000
0*
#1670000
1*
#1680000
0*
#1690000
1*
#1700000
0*
#1710000
1*
#1720000
0*
#1730000
1*
#1740000
0*
#1750000
1*
#1760000
0*
1(
#1770000
18
1*
#1780000
0*
#1790000
1-
1,
19
1*
#1800000
0*
#1810000
0-
0,
b1010 ;
b101 0
1:
1*
#1820000
0*
#1830000
1*
#1840000
0*
#1850000
1*
#1860000
0*
#1870000
1*
#1880000
0*
#1890000
1*
#1900000
0*
#1910000
1*
#1920000
b10010 >
1)
0*
0(
#1930000
16
08
1*
#1940000
0*
#1950000
09
17
1*
#1960000
0*
#1970000
0:
1*
#1980000
0*
#1990000
1*
#2000000
0*
#2010000
1*
#2020000
0*
#2030000
1*
#2040000
0*
#2050000
1*
#2060000
0*
#2070000
1*
#2080000
0*
1(
#2090000
18
1*
#2100000
0*
#2110000
1-
1,
19
1*
#2120000
0*
#2130000
0-
0,
b10101 ;
b110 0
1:
1*
#2140000
0*
#2150000
1*
#2160000
0*
#2170000
1*
#2180000
0*
#2190000
1*
#2200000
0*
#2210000
1*
#2220000
0*
#2230000
1*
#2240000
b10001 >
0)
0*
0(
#2250000
06
08
1*
#2260000
0*
#2270000
09
07
1*
#2280000
0*
#2290000
0:
1*
#2300000
0*
#2310000
1*
#2320000
0*
#2330000
1*
#2340000
0*
#2350000
1*
#2360000
0*
#2370000
1*
#2380000
0*
#2390000
1*
#2400000
0*
1(
#2410000
18
1*
#2420000
0*
#2430000
1-
1,
19
1*
#2440000
0*
#2450000
0-
0,
b101010 ;
b111 0
1:
1*
#2460000
0*
#2470000
1*
#2480000
0*
#2490000
1*
#2500000
0*
#2510000
1*
#2520000
0*
#2530000
1*
#2540000
0*
#2550000
1*
#2560000
b10000 >
1)
0*
0(
#2570000
16
08
1*
#2580000
0*
#2590000
09
17
1*
#2600000
0*
#2610000
0:
1*
#2620000
0*
#2630000
1*
#2640000
0*
#2650000
1*
#2660000
0*
#2670000
1*
#2680000
0*
#2690000
1*
#2700000
0*
#2710000
1*
#2720000
0*
1(
#2730000
18
1*
#2740000
0*
#2750000
1-
1,
19
1*
#2760000
0*
#2770000
0-
0,
b1010101 ;
b1000 0
1:
1*
#2780000
0*
#2790000
1*
#2800000
0*
#2810000
1*
#2820000
0*
#2830000
1*
#2840000
0*
#2850000
1*
#2860000
0*
#2870000
1*
#2880000
b1111 >
0)
0*
0(
#2890000
06
08
1*
#2900000
0*
#2910000
09
07
1*
#2920000
0*
#2930000
0:
1*
#2940000
0*
#2950000
1*
#2960000
0*
#2970000
1*
#2980000
0*
#2990000
1*
#3000000
0*
#3010000
1*
#3020000
0*
#3030000
1*
#3040000
0*
1(
#3050000
18
1*
#3060000
0*
#3070000
1-
1,
19
1*
#3080000
0*
#3090000
0-
0,
b10101010 ;
b1001 0
1:
1*
#3100000
0*
#3110000
1*
#3120000
0*
#3130000
1*
#3140000
0*
#3150000
1*
#3160000
0*
#3170000
1*
#3180000
0*
#3190000
1*
#3200000
b1110 >
1)
0*
0(
#3210000
16
08
1*
#3220000
0*
#3230000
09
17
1*
#3240000
0*
#3250000
0:
1*
#3260000
0*
#3270000
1*
#3280000
0*
#3290000
1*
#3300000
0*
#3310000
1*
#3320000
0*
#3330000
1*
#3340000
0*
#3350000
1*
#3360000
0*
1(
#3370000
18
1*
#3380000
0*
#3390000
1-
1,
19
1*
#3400000
0*
#3410000
0-
0,
b101010101 ;
b1010 0
1:
1*
#3420000
0*
#3430000
1*
#3440000
0*
#3450000
1*
#3460000
0*
#3470000
1*
#3480000
0*
#3490000
1*
#3500000
0*
#3510000
1*
#3520000
b1101 >
0)
0*
0(
#3530000
06
08
1*
#3540000
0*
#3550000
09
07
1*
#3560000
0*
#3570000
0:
1*
#3580000
0*
#3590000
1*
#3600000
0*
#3610000
1*
#3620000
0*
#3630000
1*
#3640000
0*
#3650000
1*
#3660000
0*
#3670000
1*
#3680000
0*
1(
#3690000
18
1*
#3700000
0*
#3710000
1-
1,
19
1*
#3720000
0*
#3730000
0-
0,
b1010101010 ;
b1011 0
1:
1*
#3740000
0*
#3750000
1*
#3760000
0*
#3770000
1*
#3780000
0*
#3790000
1*
#3800000
0*
#3810000
1*
#3820000
0*
#3830000
1*
#3840000
b1100 >
1)
0*
0(
#3850000
16
08
1*
#3860000
0*
#3870000
09
17
1*
#3880000
0*
#3890000
0:
1*
#3900000
0*
#3910000
1*
#3920000
0*
#3930000
1*
#3940000
0*
#3950000
1*
#3960000
0*
#3970000
1*
#3980000
0*
#3990000
1*
#4000000
0*
1(
#4010000
18
1*
#4020000
0*
#4030000
1-
1,
19
1*
#4040000
0*
#4050000
0-
0,
b10101010101 ;
b1100 0
1:
1*
#4060000
0*
#4070000
1*
#4080000
0*
#4090000
1*
#4100000
0*
#4110000
1*
#4120000
0*
#4130000
1*
#4140000
0*
#4150000
1*
#4160000
b1011 >
0*
0(
#4170000
08
1*
#4180000
0*
#4190000
09
1*
#4200000
0*
#4210000
0:
1*
#4220000
0*
#4230000
1*
#4240000
0*
#4250000
1*
#4260000
0*
#4270000
1*
#4280000
0*
#4290000
1*
#4300000
0*
#4310000
1*
#4320000
0*
1(
#4330000
18
1*
#4340000
0*
#4350000
1-
1,
19
1*
#4360000
0*
#4370000
0-
0,
b101010101011 ;
b1101 0
1:
1*
#4380000
0*
#4390000
1*
#4400000
0*
#4410000
1*
#4420000
0*
#4430000
1*
#4440000
0*
#4450000
1*
#4460000
0*
#4470000
1*
#4480000
b1010 >
0*
0(
#4490000
08
1*
#4500000
0*
#4510000
09
1*
#4520000
0*
#4530000
0:
1*
#4540000
0*
#4550000
1*
#4560000
0*
#4570000
1*
#4580000
0*
#4590000
1*
#4600000
0*
#4610000
1*
#4620000
0*
#4630000
1*
#4640000
0*
1(
#4650000
18
1*
#4660000
0*
#4670000
1-
1,
19
1*
#4680000
0*
#4690000
0-
0,
b1010101010111 ;
b1110 0
1:
1*
#4700000
0*
#4710000
1*
#4720000
0*
#4730000
1*
#4740000
0*
#4750000
1*
#4760000
0*
#4770000
1*
#4780000
0*
#4790000
1*
#4800000
b1001 >
0)
0*
0(
#4810000
06
08
1*
#4820000
0*
#4830000
09
07
1*
#4840000
0*
#4850000
0:
1*
#4860000
0*
#4870000
1*
#4880000
0*
#4890000
1*
#4900000
0*
#4910000
1*
#4920000
0*
#4930000
1*
#4940000
0*
#4950000
1*
#4960000
0*
1(
#4970000
18
1*
#4980000
0*
#4990000
1-
1,
19
1*
#5000000
0*
#5010000
0-
0,
b10101010101110 ;
b1111 0
1:
1*
#5020000
0*
#5030000
1*
#5040000
0*
#5050000
1*
#5060000
0*
#5070000
1*
#5080000
0*
#5090000
1*
#5100000
0*
#5110000
1*
#5120000
b1000 >
1)
0*
0(
#5130000
16
08
1*
#5140000
0*
#5150000
09
17
1*
#5160000
0*
#5170000
0:
1*
#5180000
0*
#5190000
1*
#5200000
0*
#5210000
1*
#5220000
0*
#5230000
1*
#5240000
0*
#5250000
1*
#5260000
0*
#5270000
1*
#5280000
0*
1(
#5290000
18
1*
#5300000
0*
#5310000
1-
1,
19
1*
#5320000
0*
#5330000
0-
0,
b101010101011101 ;
b10000 0
1:
1*
#5340000
0*
#5350000
1*
#5360000
0*
#5370000
1*
#5380000
0*
#5390000
1*
#5400000
0*
#5410000
1*
#5420000
0*
#5430000
1*
#5440000
b111 >
0*
0(
#5450000
08
1*
#5460000
0*
#5470000
09
1*
#5480000
0*
#5490000
0:
1*
#5500000
0*
#5510000
1*
#5520000
0*
#5530000
1*
#5540000
0*
#5550000
1*
#5560000
0*
#5570000
1*
#5580000
0*
#5590000
1*
#5600000
0*
1(
#5610000
18
1*
#5620000
0*
#5630000
1-
1,
19
1*
#5640000
0*
#5650000
0-
0,
b1010101010111011 ;
b10001 0
1:
1*
#5660000
0*
#5670000
1*
#5680000
0*
#5690000
1*
#5700000
0*
#5710000
1*
#5720000
0*
#5730000
1*
#5740000
0*
#5750000
1*
#5760000
b110 >
0*
0(
#5770000
08
1*
#5780000
0*
#5790000
09
1*
#5800000
0*
#5810000
0:
1*
#5820000
0*
#5830000
1*
#5840000
0*
#5850000
1*
#5860000
0*
#5870000
1*
#5880000
0*
#5890000
1*
#5900000
0*
#5910000
1*
#5920000
0*
1(
#5930000
18
1*
#5940000
0*
#5950000
1-
1,
19
1*
#5960000
0*
#5970000
0-
0,
b10101010101110111 ;
b10010 0
1:
1*
#5980000
0*
#5990000
1*
#6000000
0*
#6010000
1*
#6020000
0*
#6030000
1*
#6040000
0*
#6050000
1*
#6060000
0*
#6070000
1*
#6080000
b101 >
0*
0(
#6090000
08
1*
#6100000
0*
#6110000
09
1*
#6120000
0*
#6130000
0:
1*
#6140000
0*
#6150000
1*
#6160000
0*
#6170000
1*
#6180000
0*
#6190000
1*
#6200000
0*
#6210000
1*
#6220000
0*
#6230000
1*
#6240000
0*
1(
#6250000
18
1*
#6260000
0*
#6270000
1-
1,
19
1*
#6280000
0*
#6290000
0-
0,
b101010101011101111 ;
b10011 0
1:
1*
#6300000
0*
#6310000
1*
#6320000
0*
#6330000
1*
#6340000
0*
#6350000
1*
#6360000
0*
#6370000
1*
#6380000
0*
#6390000
1*
#6400000
b100 >
0)
0*
0(
#6410000
06
08
1*
#6420000
0*
#6430000
09
07
1*
#6440000
0*
#6450000
0:
1*
#6460000
0*
#6470000
1*
#6480000
0*
#6490000
1*
#6500000
0*
#6510000
1*
#6520000
0*
#6530000
1*
#6540000
0*
#6550000
1*
#6560000
0*
1(
#6570000
18
1*
#6580000
0*
#6590000
1-
1,
19
1*
#6600000
0*
#6610000
0-
0,
b1010101010111011110 ;
b10100 0
1:
1*
#6620000
0*
#6630000
1*
#6640000
0*
#6650000
1*
#6660000
0*
#6670000
1*
#6680000
0*
#6690000
1*
#6700000
0*
#6710000
1*
#6720000
b11 >
0*
0(
#6730000
08
1*
#6740000
0*
#6750000
09
1*
#6760000
0*
#6770000
0:
1*
#6780000
0*
#6790000
1*
#6800000
0*
#6810000
1*
#6820000
0*
#6830000
1*
#6840000
0*
#6850000
1*
#6860000
0*
#6870000
1*
#6880000
0*
1(
#6890000
18
1*
#6900000
0*
#6910000
1-
1,
19
1*
#6920000
0*
#6930000
0-
0,
b10101010101110111100 ;
b10101 0
1:
1*
#6940000
0*
#6950000
1*
#6960000
0*
#6970000
1*
#6980000
0*
#6990000
1*
#7000000
0*
#7010000
1*
#7020000
0*
#7030000
1*
#7040000
b10 >
1)
0*
0(
#7050000
16
08
1*
#7060000
0*
#7070000
09
17
1*
#7080000
0*
#7090000
0:
1*
#7100000
0*
#7110000
1*
#7120000
0*
#7130000
1*
#7140000
0*
#7150000
1*
#7160000
0*
#7170000
1*
#7180000
0*
#7190000
1*
#7200000
0*
1(
#7210000
18
1*
#7220000
0*
#7230000
1-
1,
19
1*
#7240000
0*
#7250000
0-
0,
b101010101011101111001 ;
b10110 0
1:
1*
#7260000
0*
#7270000
1*
#7280000
0*
#7290000
1*
#7300000
0*
#7310000
1*
#7320000
0*
#7330000
1*
#7340000
0*
#7350000
1*
#7360000
b1 >
0*
0(
#7370000
08
1*
#7380000
0*
#7390000
09
1*
#7400000
0*
#7410000
0:
1*
#7420000
0*
#7430000
1*
#7440000
0*
#7450000
1*
#7460000
0*
#7470000
1*
#7480000
0*
#7490000
1*
#7500000
0*
#7510000
1*
#7520000
0*
1(
#7530000
18
1*
#7540000
0*
#7550000
1-
1,
19
1*
#7560000
0*
#7570000
0-
0,
b1010101010111011110011 ;
b10111 0
1:
1*
#7580000
0*
#7590000
1*
#7600000
0*
#7610000
1*
#7620000
0*
#7630000
1*
#7640000
0*
#7650000
1*
#7660000
0*
#7670000
1*
#7680000
b0 >
0)
0*
0(
#7690000
06
08
1*
#7700000
0*
#7710000
09
07
1*
#7720000
0*
#7730000
0:
1*
#7740000
0*
#7750000
1*
#7760000
0*
#7770000
1*
#7780000
0*
#7790000
1*
#7800000
0*
#7810000
1*
#7820000
0*
#7830000
1*
#7840000
0*
1(
#7850000
18
1*
#7860000
0*
#7870000
1-
1,
19
1*
#7880000
0*
#7890000
0-
0,
b10101010101110111100110 ;
b11000 0
1:
1*
#7900000
0*
#7910000
1*
#7920000
0*
#7930000
1*
#7940000
0*
#7950000
1*
#7960000
0*
#7970000
1*
#7980000
0*
#7990000
1*
#8000000
b0 >
0*
0(
#8010000
08
1*
#8020000
0*
#8030000
09
1*
#8040000
0*
#8050000
0:
1*
#8060000
0*
#8070000
1*
#8080000
0*
#8090000
1*
#8100000
0*
#8110000
1*
#8120000
0*
#8130000
1*
#8140000
0*
#8150000
1*
#8160000
0*
1(
#8170000
18
1*
#8180000
0*
#8190000
1-
1,
19
1*
#8200000
0*
#8210000
0,
0-
b101010101011101111001100 ;
b11001 0
1:
1*
#8220000
0*
#8230000
1*
#8240000
0*
#8250000
1*
#8260000
0*
#8270000
1*
#8280000
0*
#8290000
1*
#8300000
0*
#8310000
1*
#8320000
b1 >
0*
0(
#8330000
08
1*
#8340000
0*
#8350000
09
1*
#8360000
0*
#8370000
0:
1*
#8380000
0*
#8390000
1*
#8400000
0*
#8410000
1*
#8420000
0*
#8430000
1*
#8440000
0*
#8450000
1*
#8460000
0*
#8470000
1*
#8480000
0*
1(
#8490000
18
1*
#8500000
0*
#8510000
1,
19
1*
#8520000
0*
#8530000
0,
b11010 0
1:
1*
#8540000
0*
#8550000
1*
#8560000
0*
#8570000
1*
#8580000
0*
#8590000
1*
#8600000
0*
#8610000
1*
#8620000
0*
#8630000
1*
#8640000
b10 >
0*
0(
#8650000
08
1*
#8660000
0*
#8670000
09
1*
#8680000
0*
#8690000
0:
1*
#8700000
0*
#8710000
1*
#8720000
0*
#8730000
1*
#8740000
0*
#8750000
1*
#8760000
0*
#8770000
1*
#8780000
0*
#8790000
1*
#8800000
0*
1(
#8810000
18
1*
#8820000
0*
#8830000
1,
19
1*
#8840000
0*
#8850000
0,
b11011 0
1:
1*
#8860000
0*
#8870000
1*
#8880000
0*
#8890000
1*
#8900000
0*
#8910000
1*
#8920000
0*
#8930000
1*
#8940000
0*
#8950000
1*
#8960000
b11 >
0*
0(
#8970000
08
1*
#8980000
0*
#8990000
09
1*
#9000000
0*
#9010000
0:
1*
#9020000
0*
#9030000
1*
#9040000
0*
#9050000
1*
#9060000
0*
#9070000
1*
#9080000
0*
#9090000
1*
#9100000
0*
#9110000
1*
#9120000
0*
1(
#9130000
18
1*
#9140000
0*
#9150000
1,
19
1*
#9160000
0*
#9170000
0,
b11100 0
1:
1*
#9180000
0*
#9190000
1*
#9200000
0*
#9210000
1*
#9220000
0*
#9230000
1*
#9240000
0*
#9250000
1*
#9260000
0*
#9270000
1*
#9280000
b100 >
0*
0(
#9290000
08
1*
#9300000
0*
#9310000
09
1*
#9320000
0*
#9330000
0:
1*
#9340000
0*
#9350000
1*
#9360000
0*
#9370000
1*
#9380000
0*
#9390000
1*
#9400000
0*
#9410000
1*
#9420000
0*
#9430000
1*
#9440000
0*
1(
#9450000
18
1*
#9460000
0*
#9470000
1,
19
1*
#9480000
0*
#9490000
0,
b11101 0
1:
1*
#9500000
0*
#9510000
1*
#9520000
0*
#9530000
1*
#9540000
0*
#9550000
1*
#9560000
0*
#9570000
1*
#9580000
0*
#9590000
1*
#9600000
b101 >
0*
0(
#9610000
08
1*
#9620000
0*
#9630000
09
1*
#9640000
0*
#9650000
0:
1*
#9660000
0*
#9670000
1*
#9680000
0*
#9690000
1*
#9700000
0*
#9710000
1*
#9720000
0*
#9730000
1*
#9740000
0*
#9750000
1*
#9760000
0*
1(
#9770000
18
1*
#9780000
0*
#9790000
1,
19
1*
#9800000
0*
#9810000
0,
b11110 0
1:
1*
#9820000
0*
#9830000
1*
#9840000
0*
#9850000
1*
#9860000
0*
#9870000
1*
#9880000
0*
#9890000
1*
#9900000
0*
#9910000
1*
#9920000
b110 >
0*
0(
#9930000
08
1*
#9940000
0*
#9950000
09
1*
#9960000
0*
#9970000
0:
1*
#9980000
0*
#9990000
1*
#10000000
0*
#10010000
1*
#10020000
0*
#10030000
1*
#10040000
0*
#10050000
1*
#10060000
0*
#10070000
1*
#10080000
0*
1(
#10090000
18
1*
#10100000
0*
#10110000
1,
19
1*
#10120000
0*
#10130000
0,
b11111 0
1:
1*
#10140000
0*
#10150000
1*
#10160000
0*
#10170000
1*
#10180000
0*
#10190000
1*
#10200000
0*
#10210000
1*
#10220000
0*
#10230000
1*
#10240000
b111 >
0*
0(
#10250000
08
1*
#10260000
0*
#10270000
09
1*
#10280000
0*
#10290000
0:
1*
#10300000
0*
#10310000
1*
#10320000
0*
#10330000
1*
#10340000
0*
#10350000
1*
#10360000
0*
#10370000
1*
#10380000
0*
#10390000
1*
#10400000
1<
b100010010001000110011 =
0*
1(
#10410000
18
1*
#10420000
0*
#10430000
1,
19
1*
#10440000
0*
#10450000
0,
b100000 0
1:
1*
#10460000
0*
#10470000
1*
#10480000
0*
#10490000
1*
#10500000
0*
#10510000
1*
#10520000
0*
#10530000
1*
#10540000
0*
#10550000
1*
#10560000
b10111 >
1&
0*
0(
#10570000
12
08
1*
#10580000
0*
#10590000
1+
09
13
1*
#10600000
0*
#10610000
0+
b101010101011101111001100 #
b101010101011101111001100 1
b0 0
14
0:
1*
#10620000
0*
#10630000
1*
#10640000
0*
#10650000
1*
#10660000
0*
#10670000
1*
#10680000
0*
#10690000
1*
#10700000
0*
#10710000
1*
#10720000
0*
1(
#10730000
18
1*
#10740000
0*
#10750000
1,
19
1*
#10760000
0*
#10770000
0-
0,
b1 0
1:
1*
#10780000
0*
#10790000
1*
#10800000
0*
#10810000
1*
#10820000
0*
#10830000
1*
#10840000
0*
#10850000
1*
#10860000
0*
#10870000
1*
#10880000
b10110 >
0*
0(
#10890000
08
1*
#10900000
0*
#10910000
09
1*
#10920000
0*
#10930000
0:
1*
#10940000
0*
#10950000
1*
#10960000
0*
#10970000
1*
#10980000
0*
#10990000
1*
#11000000
0*
#11010000
1*
#11020000
0*
#11030000
1*
#11040000
0*
1(
#11050000
18
1*
#11060000
0*
#11070000
1-
1,
19
1*
#11080000
0*
#11090000
0-
0,
b10101010111011110011000 ;
b10 0
1:
1*
#11100000
0*
#11110000
1*
#11120000
0*
#11130000
1*
#11140000
0*
#11150000
1*
#11160000
0*
#11170000
1*
#11180000
0*
#11190000
1*
#11200000
b10101 >
0*
0(
#11210000
08
1*
#11220000
0*
#11230000
09
1*
#11240000
0*
#11250000
0:
1*
#11260000
0*
#11270000
1*
#11280000
0*
#11290000
1*
#11300000
0*
#11310000
1*
#11320000
0*
#11330000
1*
#11340000
0*
#11350000
1*
#11360000
0*
1(
#11370000
18
1*
#11380000
0*
#11390000
1-
1,
19
1*
#11400000
0*
#11410000
0-
0,
b101010101110111100110000 ;
b11 0
1:
1*
#11420000
0*
#11430000
1*
#11440000
0*
#11450000
1*
#11460000
0*
#11470000
1*
#11480000
0*
#11490000
1*
#11500000
0*
#11510000
1*
#11520000
b10100 >
0*
0(
#11530000
08
1*
#11540000
0*
#11550000
09
1*
#11560000
0*
#11570000
0:
1*
#11580000
0*
#11590000
1*
#11600000
0*
#11610000
1*
#11620000
0*
#11630000
1*
#11640000
0*
#11650000
1*
#11660000
0*
#11670000
1*
#11680000
0*
1(
#11690000
18
1*
#11700000
0*
