rtl/synthesizer/triangle_wave.v
`timescale 1ns/1ps
module triangle_wave #(
    parameter AMP_WIDTH=16,
    parameter PHASE_WIDTH= 32
)(
    input [PHASE_WIDTH-1:0]phase_in,
    output reg signed [AMP_WIDTH-1:0]amplitude
);
always @(*)
begin
    if(phase_in < (1<<(PHASE_WIDTH-2)) )
    begin
        amplitude = (((1<<(AMP_WIDTH-1))-1)*phase_in)/(1<<(PHASE_WIDTH-2));
    end
    else if(phase_in<(1<<(PHASE_WIDTH-1)))
    begin
        amplitude = ((1<<(AMP_WIDTH-1))-1)-(((1<<(AMP_WIDTH-1))-1)*(phase_in - (1<<(PHASE_WIDTH-2)))/(1<<(PHASE_WIDTH-2)));
    end
    else if(phase_in < 3*(1<<(PHASE_WIDTH-2)))
    begin
        amplitude = -((((1<<(AMP_WIDTH-1))-1)*(phase_in - (1<<(PHASE_WIDTH-1))))/(1<<(PHASE_WIDTH-2)));
    end
    else
    begin
        amplitude = -((1<<(AMP_WIDTH-1))-1) + (((1<<(AMP_WIDTH-1))-1)*(phase_in-(3*(1<<(PHASE_WIDTH-2))))/(1<<(PHASE_WIDTH-2)));
    end
end
endmodule

tb/synthesizer/triangle_wave_tb.v
`timescale 1ns/1ps
module triangle_wave_tb();
reg [31:0]phase_in_tb;
wire signed [15:0]amplitude_tb;
triangle_wave DUT(
    .phase_in(phase_in_tb),
    .amplitude(amplitude_tb)
);
initial
begin
    $dumpfile("sim/triangle_wave.vcd");
    $dumpvars(0,triangle_wave_tb);
    phase_in_tb = 0 ; #10
    phase_in_tb=(1<<(29));#10
    phase_in_tb=(1<<(30));#10
    phase_in_tb=3*(1<<(29));#10
    phase_in_tb=(1<<(31));#10
    phase_in_tb=5*(1<<(29));#10
    phase_in_tb=3*(1<<(30));#10
    phase_in_tb=7*(1<<(29));#10
    phase_in_tb=0;
    $finish;
end 
endmodule

sim/synthesizer/triangle_wave.vcd
$date
	Sun Aug 30 09:51:23 2026
$end
$version
	Icarus Verilog
$end
$timescale
	1ps
$end
$scope module triangle_wave_tb $end
$var wire 16 ! amplitude_tb [15:0] $end
$var reg 32 " phase_in_tb [31:0] $end
$scope module DUT $end
$var wire 32 # phase_in [31:0] $end
$var parameter 32 $ AMP_WIDTH $end
$var parameter 32 % PHASE_WIDTH $end
$var reg 16 & amplitude [15:0] $end
$upscope $end
$upscope $end
$enddefinitions $end
$comment Show the parameter values. $end
$dumpall
b100000 %
b10000 $
$end
#0
$dumpvars
b0 &
b0 #
b0 "
b0 !
$end
#10000
b11 !
b11 &
b100000000000000000000000000000 "
b100000000000000000000000000000 #
#20000
b111111111111111 !
b111111111111111 &
b1000000000000000000000000000000 "
b1000000000000000000000000000000 #
#30000
b111111111111100 !
b111111111111100 &
b1100000000000000000000000000000 "
b1100000000000000000000000000000 #
#40000
b0 !
b0 &
b10000000000000000000000000000000 "
b10000000000000000000000000000000 #
#50000
b1111111111111101 !
b1111111111111101 &
b10100000000000000000000000000000 "
b10100000000000000000000000000000 #
#60000
b1000000000000001 !
b1000000000000001 &
b11000000000000000000000000000000 "
b11000000000000000000000000000000 #
#70000
b1000000000000100 !
b1000000000000100 &
b11100000000000000000000000000000 "
b11100000000000000000000000000000 #
#80000
b0 !
b0 &
b0 "
b0 #
